onnx_model_maker/__init__.py
onnx_model_maker/code_gen.py
onnx_model_maker/ops/__init__.py
onnx_model_maker/ops/op_helper.py
onnx_model_maker/ops/op_ver_1.py
onnx_model_maker/ops/op_ver_10.py
onnx_model_maker/ops/op_ver_11.py
onnx_model_maker/ops/op_ver_12.py
onnx_model_maker/ops/op_ver_13.py
onnx_model_maker/ops/op_ver_14.py
onnx_model_maker/ops/op_ver_15.py
onnx_model_maker/ops/op_ver_16.py
onnx_model_maker/ops/op_ver_17.py
onnx_model_maker/ops/op_ver_2.py
onnx_model_maker/ops/op_ver_3.py
onnx_model_maker/ops/op_ver_4.py
onnx_model_maker/ops/op_ver_5.py
onnx_model_maker/ops/op_ver_6.py
onnx_model_maker/ops/op_ver_7.py
onnx_model_maker/ops/op_ver_8.py
onnx_model_maker/ops/op_ver_9.py
onnx_pytorch/__init__.py
onnx_pytorch/_version.py
onnx_pytorch/code_gen.py
onnx_pytorch/code_gen_template.py
onnx_pytorch/op_code_generators/Abs.py
onnx_pytorch/op_code_generators/Acos.py
onnx_pytorch/op_code_generators/Acosh.py
onnx_pytorch/op_code_generators/Add.py
onnx_pytorch/op_code_generators/And.py
onnx_pytorch/op_code_generators/ArgMax.py
onnx_pytorch/op_code_generators/ArgMin.py
onnx_pytorch/op_code_generators/Asin.py
onnx_pytorch/op_code_generators/Asinh.py
onnx_pytorch/op_code_generators/Atan.py
onnx_pytorch/op_code_generators/Atanh.py
onnx_pytorch/op_code_generators/AveragePool.py
onnx_pytorch/op_code_generators/BatchNormalization.py
onnx_pytorch/op_code_generators/BitShift.py
onnx_pytorch/op_code_generators/Cast.py
onnx_pytorch/op_code_generators/Ceil.py
onnx_pytorch/op_code_generators/Clip.py
onnx_pytorch/op_code_generators/Concat.py
onnx_pytorch/op_code_generators/Constant.py
onnx_pytorch/op_code_generators/ConstantOfShape.py
onnx_pytorch/op_code_generators/Conv.py
onnx_pytorch/op_code_generators/ConvTranspose.py
onnx_pytorch/op_code_generators/Cos.py
onnx_pytorch/op_code_generators/Cosh.py
onnx_pytorch/op_code_generators/Div.py
onnx_pytorch/op_code_generators/Dropout.py
onnx_pytorch/op_code_generators/Elu.py
onnx_pytorch/op_code_generators/Equal.py
onnx_pytorch-0.1.5.dist-info/LICENSE
onnx_pytorch-0.1.5.dist-info/METADATA
onnx_pytorch-0.1.5.dist-info/WHEEL
onnx_pytorch-0.1.5.dist-info/top_level.txt
onnx_pytorch-0.1.5.dist-info/RECORD
