Metadata-Version: 2.1
Name: onnx-pytorch
Version: 0.1.5
Summary: Convert ONNX to PyTorch code.
Home-page: https://github.com/fumihwh/onnx-pytorch
Author: fumihwh
Author-email: fumihwh@gmail.com
License: Apache 2.0
Classifier: Programming Language :: Python :: 3
License-File: LICENSE
Requires-Dist: numpy (>=1.19.5)
Requires-Dist: onnx (>=1.10.2)
Requires-Dist: onnxruntime (>=1.9.0)
Requires-Dist: pytest (>=6.2.5)
Requires-Dist: PyYAML (>=6.0)
Requires-Dist: setuptools (>=59.2.0)
Requires-Dist: sympy (>=1.9)
Requires-Dist: torch (>=1.10.0)
Requires-Dist: torchvision (>=0.11.1)
Requires-Dist: tqdm (>=4.62.3)
